blank_project/__init__.py
blank_project-0.3.1.dist-info/LICENSE
blank_project-0.3.1.dist-info/METADATA
blank_project-0.3.1.dist-info/WHEEL
blank_project-0.3.1.dist-info/top_level.txt
blank_project-0.3.1.dist-info/RECORD
