Metadata-Version: 2.1
Name: blank-project
Version: 0.3.1
Summary: A dummy package for quickly starting typical Python projects.
Author-email: Peter Bro <p3t3rbr0@gmail.com>
Project-URL: Homepage, https://git.peterbro.su/peter/py3-blank-project
Project-URL: Documentation, https://git.peterbro.su/peter/py3-blank-project/src/branch/master/README.md
Project-URL: Repository, https://git.peterbro.su/peter/py3-blank-project.git
Project-URL: Issues, https://git.peterbro.su/peter/py3-blank-project/issues
Project-URL: Changelog, https://git.peterbro.su/peter/py3-blank-project/src/branch/master/CHANGELOG.md
Keywords: utility,dummy package
Classifier: Development Status :: 3 - Alpha
Classifier: Intended Audience :: Developers
Classifier: License :: OSI Approved :: MIT License
Classifier: Operating System :: OS Independent
Classifier: Programming Language :: Python :: 3
Classifier: Programming Language :: Python :: 3.10
Classifier: Programming Language :: Python :: 3.11
Classifier: Programming Language :: Python :: 3.12
Classifier: Programming Language :: Python :: 3.13
Classifier: Topic :: Software Development
Classifier: Topic :: Software Development :: Libraries
Classifier: Topic :: Software Development :: Libraries :: Python Modules
Classifier: Typing :: Typed
Requires-Python: >=3.10
License-File: LICENSE
Provides-Extra: build
Requires-Dist: build ==1.2.2.post1 ; extra == 'build'
Requires-Dist: twine ==5.1.1 ; extra == 'build'
Provides-Extra: dev
Requires-Dist: coverage ==7.6.4 ; extra == 'dev'
Requires-Dist: mypy ==1.13.0 ; extra == 'dev'
Requires-Dist: isort ==5.13.2 ; extra == 'dev'
Requires-Dist: flake8 ==7.1.1 ; extra == 'dev'
Requires-Dist: black ==24.10.0 ; extra == 'dev'
Requires-Dist: pydocstyle ==6.3.0 ; extra == 'dev'
